flake8_pyi/__init__.py
flake8_pyi/checker.py
flake8_pyi/errors.py
flake8_pyi/visitor.py
flake8_pyi-25.5.0.dist-info/METADATA
flake8_pyi-25.5.0.dist-info/WHEEL
flake8_pyi-25.5.0.dist-info/entry_points.txt
flake8_pyi-25.5.0.dist-info/licenses/LICENSE
flake8_pyi-25.5.0.dist-info/RECORD
