Metadata-Version: 2.4
Name: flake8-pyi
Version: 25.5.0
Summary: A plugin for flake8 to enable linting .pyi stub files.
Project-URL: Homepage, https://github.com/PyCQA/flake8-pyi
Project-URL: Source, https://github.com/PyCQA/flake8-pyi
Project-URL: Bug Tracker, https://github.com/PyCQA/flake8-pyi/issues
Project-URL: Changelog, https://github.com/PyCQA/flake8-pyi/blob/main/CHANGELOG.md
Author-email: Łukasz Langa <=lukasz@langa.pl>
Maintainer: Akuli, Shantanu
Maintainer-email: Jelle Zijlstra <jelle.zijlstra@gmail.com>, Alex Waygood <alex.waygood@gmail.com>, Sebastian Rittau <sebastian@rittau.biz>
License-Expression: MIT
License-File: LICENSE
Keywords: bugs,flake8,linter,pyflakes,pyi,qa,stubs,typing
Classifier: Development Status :: 5 - Production/Stable
Classifier: Environment :: Console
Classifier: Framework :: Flake8
Classifier: Intended Audience :: Developers
Classifier: Operating System :: OS Independent
Classifier: Programming Language :: Python
Classifier: Programming Language :: Python :: 3 :: Only
Classifier: Programming Language :: Python :: 3.9
Classifier: Programming Language :: Python :: 3.10
Classifier: Programming Language :: Python :: 3.11
Classifier: Programming Language :: Python :: 3.12
Classifier: Programming Language :: Python :: 3.13
Classifier: Programming Language :: Python :: 3.14
Classifier: Topic :: Software Development :: Libraries :: Python Modules
Classifier: Topic :: Software Development :: Quality Assurance
Requires-Python: >=3.9
Requires-Dist: flake8<8.0.0,>=6.0.0
Requires-Dist: pyflakes>=2.1.1
